{
  "slug": "galston",
  "title": "Galston Studienbuch",
  "path": "/galston",
  "nav": [
    {
      "to": "/galston",
      "text": "Introduction"
    },
    {
      "to": "/galston/studienbuch",
      "text": "The Studienbuch"
    },
    {
      "to": "/galston/concert-programs",
      "text": "Concert Programs"
    },
    {
      "to": "/galston/gottfried-galston",
      "text": "About Galston"
    },
    {
      "to": "/galston/resources",
      "text": "Resources"
    }
  ],
  "styles": "exhibits/galston.scss"
}
